fast_transfer/__about__.py
fast_transfer/__init__.py
fast_transfer/app.py
fast_transfer/static/bulma.min.css
fast_transfer/static/icons/file.svg
fast_transfer/static/icons/folder.svg
fast_transfer/static/icons/image.svg
fast_transfer/templates/index.html
fast_transfer-0.2.2.dist-info/METADATA
fast_transfer-0.2.2.dist-info/WHEEL
fast_transfer-0.2.2.dist-info/entry_points.txt
fast_transfer-0.2.2.dist-info/licenses/LICENSE
fast_transfer-0.2.2.dist-info/RECORD
